{
  "workflow": "overnight",
  "ok": true,
  "note": "523 rows, last 2026-05-19",
  "as_of": "2026-05-19T14:11:59+00:00",
  "github": {
    "run_id": "26102807333",
    "run_number": "29",
    "ref": "refs/heads/main",
    "sha": "544a481932cfc78972d93c81818b2fb2c8dae39d"
  },
  "payload": {
    "rows": 523,
    "last_date": "2026-05-19",
    "tickers": [
      "sp500",
      "vix",
      "nikkei",
      "hangseng",
      "ftse",
      "dxy",
      "fm_etf",
      "eem",
      "nifty",
      "kospi",
      "sti",
      "shanghai",
      "us10y",
      "usd_inr",
      "usd_cny",
      "eur_usd"
    ]
  }
}