{
  "workflow": "predictions",
  "ok": true,
  "note": "35 new predictions, 412 in log",
  "as_of": "2026-05-12T11:34:26+00:00",
  "github": {
    "run_id": "25731707115",
    "run_number": "48",
    "ref": "refs/heads/main",
    "sha": "93416407cd088a7c909f0cdd51132d91f8f069de"
  },
  "payload": {
    "new": 35,
    "total": 412,
    "symbols": [
      "HUBC",
      "PABC",
      "MLCF",
      "OGDC",
      "FABL",
      "PPL",
      "NPL",
      "POL",
      "FCCL",
      "APL",
      "EPCL",
      "KOHC",
      "SEARL",
      "MCB",
      "MEBL",
      "PSO",
      "HBL",
      "UBL",
      "BAHL",
      "NBP",
      "MARI",
      "LUCK",
      "DGKC",
      "FFC",
      "EFERT",
      "FATIMA",
      "KAPCO",
      "KEL",
      "ATRL",
      "ENGROH",
      "LOTCHEM",
      "SYS",
      "TRG",
      "INDU",
      "COLG"
    ]
  }
}